dtpystreamer/__init__.py
dtpystreamer/consumer.py
dtpystreamer/sender.py
dtpystreamer-1.0.4.dist-info/METADATA
dtpystreamer-1.0.4.dist-info/WHEEL
dtpystreamer-1.0.4.dist-info/RECORD
