Metadata-Version: 2.3
Name: dtpystreamer
Version: 1.0.4
Summary: A package to send and receive messages using Redis streams
License: MIT
Author: Reza Shirazi
Author-email: reza@datgate.com
Requires-Python: >=3.11.9,<3.12.0
Classifier: License :: OSI Approved :: MIT License
Classifier: Programming Language :: Python :: 3
Requires-Dist: dtpyredis (>=1.0.0,<1.1.0)
Requires-Dist: dtpyutils (>=1.0.0,<1.1.0)
